ItsPrompt/keyboard_handler.py
ItsPrompt/prompt.py
ItsPrompt/py.typed
ItsPrompt/data/__init__.py
ItsPrompt/data/checkbox.py
ItsPrompt/data/expand.py
ItsPrompt/data/select.py
ItsPrompt/data/style.py
ItsPrompt/data/table.py
ItsPrompt/objects/prompts/option.py
ItsPrompt/objects/prompts/options_with_separator.py
ItsPrompt/objects/prompts/separator.py
ItsPrompt/objects/prompts/type.py
ItsPrompt/objects/table/table_base.py
ItsPrompt/objects/table/table_df.py
ItsPrompt/objects/table/table_dict.py
ItsPrompt/objects/table/table_list.py
ItsPrompt/prompts/__init__.py
ItsPrompt/prompts/checkbox.py
ItsPrompt/prompts/confirm.py
ItsPrompt/prompts/expand.py
ItsPrompt/prompts/input.py
ItsPrompt/prompts/raw_select.py
ItsPrompt/prompts/select.py
ItsPrompt/prompts/table.py
ItsPrompt-1.5.dist-info/LICENSE
ItsPrompt-1.5.dist-info/METADATA
ItsPrompt-1.5.dist-info/WHEEL
ItsPrompt-1.5.dist-info/top_level.txt
ItsPrompt-1.5.dist-info/RECORD
