Metadata-Version: 2.1
Name: ItsPrompt
Version: 1.5
Summary: Prompting - the fancy way
Author: ItsNameless
License: MIT License
Project-URL: Homepage, https://github.com/TheItsProjects/ItsPrompt
Project-URL: Repository, https://github.com/TheItsProjects/ItsPrompt
Project-URL: Issue Tracker, https://github.com/TheItsProjects/ItsPrompt/issues
Classifier: Programming Language :: Python :: 3
Classifier: License :: OSI Approved :: MIT License
Classifier: Operating System :: OS Independent
Requires-Python: >=3.8
License-File: LICENSE
Requires-Dist: prompt-toolkit <4.0,>=3.0.37
